simple_CLI_builder/__init__.py
simple_CLI_builder/main.py
simple_CLI_builder-0.4.dist-info/LICENSE
simple_CLI_builder-0.4.dist-info/METADATA
simple_CLI_builder-0.4.dist-info/WHEEL
simple_CLI_builder-0.4.dist-info/top_level.txt
simple_CLI_builder-0.4.dist-info/RECORD
