Metadata-Version: 2.1
Name: simple_CLI_builder
Version: 0.4
License-File: LICENSE
